[{"line":2,"elements":[{"start_timestamp":"2022-08-01T02:54:34.365Z","line":5,"name":"Opening a webpage using Selenium","description":"","id":"first-test;opening-a-webpage-using-selenium","type":"scenario","keyword":"Scenario","steps":[{"result":{"duration":11352126100,"status":"passed"},"line":6,"name":"User is on Google Home Page","match":{"location":"stepDefinitions.GoogleSearchSteps.googleHomePage()"},"keyword":"Given "},{"result":{"duration":289311200,"status":"passed"},"line":7,"name":"User types in Cheese and hits ENTER","match":{"location":"stepDefinitions.GoogleSearchSteps.googleSearch()"},"keyword":"When "},{"result":{"duration":1214945300,"status":"passed"},"line":8,"name":"Show how many search results were shown","match":{"location":"stepDefinitions.GoogleSearchSteps.showHowManySearchResultsAreShown()"},"keyword":"Then "},{"result":{"duration":1862212900,"status":"passed"},"line":9,"name":"Close the browser","match":{"location":"stepDefinitions.CloseBrowser.closeBrowser()"},"keyword":"And "}],"tags":[{"name":"@activity1"},{"name":"@SmokeTest"}]}],"name":"First Test","description":"","id":"first-test","keyword":"Feature","uri":"file:src/test/java/Features/Activity1.feature","tags":[{"name":"@activity1","type":"Tag","location":{"line":1,"column":1}}]},{"line":2,"elements":[{"start_timestamp":"2022-08-01T02:54:49.142Z","line":15,"name":"Testing with Simple Alert","description":"","id":"testing-with-tags;testing-with-simple-alert","type":"scenario","keyword":"Scenario","steps":[{"result":{"duration":7163321200,"status":"passed"},"line":16,"name":"User is on the page","match":{"location":"stepDefinitions.TestingWithTags.alertTestPage()"},"keyword":"Given "},{"result":{"duration":382651800,"status":"passed"},"line":17,"name":"User clicks the Simple Alert button","match":{"location":"stepDefinitions.TestingWithTags.simpleAlertTest()"},"keyword":"When "},{"result":{"duration":21100300,"status":"passed"},"line":18,"name":"Alert opens","match":{"location":"stepDefinitions.TestingWithTags.switchFocus()"},"keyword":"Then "},{"result":{"duration":15991000,"status":"passed"},"line":19,"name":"Read the text from it and print it","match":{"location":"stepDefinitions.TestingWithTags.readAlert()"},"keyword":"And "},{"result":{"duration":37911800,"status":"passed"},"line":20,"name":"Close the alert","match":{"location":"stepDefinitions.TestingWithTags.acceptAndCloseAlert()"},"keyword":"And "},{"result":{"duration":1867933400,"status":"passed"},"line":21,"name":"Close the browser","match":{"location":"stepDefinitions.CloseBrowser.closeBrowser()"},"keyword":"And "}],"tags":[{"name":"@activity3"},{"name":"@SimpleAlert"},{"name":"@SmokeTest"}]}],"name":"Testing with Tags","description":"","id":"testing-with-tags","keyword":"Feature","uri":"file:src/test/java/Features/Activity3.feature","tags":[{"name":"@activity3","type":"Tag","location":{"line":1,"column":1}}]}]